{"guide_changelog.md":"lkNRtTY0","guide_components_alert.md":"BYz1Ap2q","guide_components_avatar.md":"D5Y0UFP7","guide_components_backtop.md":"B6gWgErS","guide_components_badge.md":"DvZU9V8C","guide_components_breadcrumb.md":"C1T-kSU4","guide_components_button.md":"HWHfcP9k","guide_components_card.md":"8eOg7Cg_","guide_components_carousel.md":"CE5-e0_-","guide_components_cascader.md":"B035NmTV","guide_components_checkbox.md":"CbzrKO95","guide_components_collapse.md":"yB41XxGU","guide_components_countdown.md":"CrmuTkt6","guide_components_datepicker.md":"BTBi5p76","guide_components_descriptions.md":"BL3r2KJN","guide_components_dialog.md":"B-vGIwAY","guide_components_divider.md":"DJaYY_J3","guide_components_drawer.md":"CQ1E85Yw","guide_components_ellipsis.md":"D13KvUpR","guide_components_empty.md":"B4kNTnL6","guide_components_flex.md":"CXmb3srH","guide_components_gradienttext.md":"EyyuywbQ","guide_components_grid.md":"BsFKfiCD","guide_components_image.md":"D5rAqrTT","guide_components_input.md":"B068x-dz","guide_components_inputnumber.md":"BjZy9ed5","guide_components_message.md":"Cb1P5DYG","guide_components_modal.md":"DrDhNSJl","guide_components_notification.md":"CMapxuBD","guide_components_numberanimation.md":"BAK7gizs","guide_components_pagination.md":"C6MlQEFj","guide_components_popconfirm.md":"CjFw4DD0","guide_components_popover.md":"DxL5jskU","guide_components_progress.md":"k6REl2Re","guide_components_qrcode.md":"Dyk0CiZ-","guide_components_radio.md":"CzqH_nhO","guide_components_rate.md":"5eFr5UYj","guide_components_result.md":"jwOotYPO","guide_components_scrollbar.md":"CIabVfXi","guide_components_select.md":"B5Y2A2aQ","guide_components_skeleton.md":"DM_ud7NZ","guide_components_slider.md":"B1TPeOaS","guide_components_space.md":"CguZQ6cA","guide_components_spin.md":"BajWzuca","guide_components_statistic.md":"O1a86U4X","guide_components_steps.md":"CiGXkv71","guide_components_swiper.md":"CdCdhFTE","guide_components_switch.md":"CDPrjGYY","guide_components_table.md":"Cl2j46m9","guide_components_tabs.md":"CiDJQz7x","guide_components_tag.md":"BRgP5lYf","guide_components_textarea.md":"DcTANZLR","guide_components_textscroll.md":"CU91Ghyb","guide_components_timeline.md":"CLLMNNsQ","guide_components_tooltip.md":"Dn6QMtwG","guide_components_upload.md":"p2XBBpIP","guide_components_video.md":"CvTzTy8R","guide_components_waterfall.md":"BdqmU-aU","guide_components_watermark.md":"osRXANxO","guide_features.md":"D3nLiZZ_","guide_started.md":"fHw5XOtn","index.md":"CP0_bpr1","utils_functions_add.md":"CnSgq5Rb","utils_functions_date-format.md":"t38WItCz","utils_functions_debounce.md":"iu69QL2H","utils_functions_download-file.md":"D7StXELs","utils_functions_event-listener.md":"BptkkObT","utils_functions_format-number.md":"D95BEgTT","utils_functions_fps.md":"ZCXlT4EI","utils_functions_media-query.md":"BsLBQzjq","utils_functions_mutation-observer.md":"BQ-ZmjXA","utils_functions_raf-timeout.md":"C_GNF264","utils_functions_resize-observer.md":"bNwqpxt2","utils_functions_scroll-direction.md":"BmWCX6ng","utils_functions_throttle.md":"Bu-8GAA_","utils_functions_toggle-dark.md":"DdLvdTg-","utils_started.md":"BP0s_mb5"}
