{"guide_changelog.md":"DWGvpBn6","guide_components_alert.md":"BQgXUi5d","guide_components_avatar.md":"BpRoMpDc","guide_components_backtop.md":"ChncTA3F","guide_components_badge.md":"CBdfzs_N","guide_components_breadcrumb.md":"uWusvcUb","guide_components_button.md":"ogN06VHk","guide_components_card.md":"CLMflVyp","guide_components_carousel.md":"CFkwnvSb","guide_components_cascader.md":"Du1HrXt7","guide_components_checkbox.md":"NYf4rtI2","guide_components_collapse.md":"DdCV2A0o","guide_components_countdown.md":"BNR8at8e","guide_components_datepicker.md":"D7O7nFwr","guide_components_descriptions.md":"D1pondYb","guide_components_dialog.md":"DIdC0ZeW","guide_components_divider.md":"CaeUCfzu","guide_components_drawer.md":"BAQjlCMO","guide_components_ellipsis.md":"OZSj4V4K","guide_components_empty.md":"D8zgnFIu","guide_components_flex.md":"CKPQcy8M","guide_components_gradienttext.md":"jne5Wr2p","guide_components_grid.md":"ByMvJZ4U","guide_components_image.md":"Ct7ApBvp","guide_components_input.md":"CarrhhAR","guide_components_inputnumber.md":"cwxF4xnW","guide_components_loadingbar.md":"D-AoQGsG","guide_components_message.md":"CcAl2H7k","guide_components_modal.md":"YGSSxqyV","guide_components_notification.md":"BJvIZPJG","guide_components_numberanimation.md":"CR53BPV-","guide_components_pagination.md":"0W9aU6V8","guide_components_popconfirm.md":"CH9cTmjk","guide_components_popover.md":"DpHb3zQW","guide_components_progress.md":"B9X3Ysfx","guide_components_qrcode.md":"BzJSDU4n","guide_components_radio.md":"Gjg4ANGP","guide_components_rate.md":"CeGeJ9Yt","guide_components_result.md":"ISu26PCy","guide_components_scrollbar.md":"BGxrqerV","guide_components_segmented.md":"DVOpg23C","guide_components_select.md":"Boz2mIdg","guide_components_skeleton.md":"jSTiMJie","guide_components_slider.md":"DJOlyerv","guide_components_space.md":"BVSP-O5K","guide_components_spin.md":"3IiC_eEb","guide_components_statistic.md":"CuaE2mi_","guide_components_steps.md":"Bx1Yb_fq","guide_components_swiper.md":"EBeRYCKk","guide_components_switch.md":"H9_VP5UP","guide_components_table.md":"Cezf74Sy","guide_components_tabs.md":"CMul-CCP","guide_components_tag.md":"Dc65ykax","guide_components_textarea.md":"B94qMSiC","guide_components_textscroll.md":"V7-wl-XL","guide_components_timeline.md":"CtvO9ata","guide_components_tooltip.md":"D7CCsr62","guide_components_upload.md":"CEeuWnst","guide_components_video.md":"DkTbFKXR","guide_components_waterfall.md":"UDc5rj8l","guide_components_watermark.md":"DdoHBbgT","guide_features.md":"BQTSwW7h","guide_started.md":"C1uKLDNY","index.md":"6s5W9brP","utils_functions_add.md":"BPvknZa_","utils_functions_date-format.md":"SgjPeMX2","utils_functions_debounce.md":"MBz90RUb","utils_functions_download-file.md":"DbJTl9fA","utils_functions_event-listener.md":"Dsywf-X-","utils_functions_format-number.md":"tq2HypPU","utils_functions_fps.md":"BHHwawVO","utils_functions_media-query.md":"BCHuU65n","utils_functions_mutation-observer.md":"kMNiFlx1","utils_functions_raf-timeout.md":"m6dVV7UI","utils_functions_resize-observer.md":"BRlqA7tE","utils_functions_scroll-direction.md":"yqes_QAD","utils_functions_throttle.md":"B_Nvu6Oe","utils_functions_toggle-dark.md":"NbeQdsfG","utils_started.md":"BNXuJZGC"}
