{"guide_changelog.md":"BLajOgTu","guide_components_alert.md":"O53TM8M-","guide_components_avatar.md":"DcRG_c7V","guide_components_backtop.md":"CHVRLaUP","guide_components_badge.md":"DyS3gp8O","guide_components_breadcrumb.md":"DnFq0K11","guide_components_button.md":"D4tJ2yg_","guide_components_calendar.md":"hEMmmPCJ","guide_components_card.md":"B0wOj10u","guide_components_carousel.md":"ffO5SE12","guide_components_cascader.md":"DtTh0mWt","guide_components_checkbox.md":"DRMk_eJc","guide_components_collapse.md":"C8E7BL7k","guide_components_colorpicker.md":"CAIJg00j","guide_components_configprovider.md":"BotRAWho","guide_components_countdown.md":"CIyB7WO1","guide_components_datepicker.md":"BgGkZkmM","guide_components_descriptions.md":"CuEqE00e","guide_components_dialog.md":"CHNH350t","guide_components_divider.md":"jy5pJJQH","guide_components_drawer.md":"B7_b1UwB","guide_components_ellipsis.md":"-a95YmTs","guide_components_empty.md":"km3Onu2m","guide_components_flex.md":"CXCOLQYl","guide_components_floatbutton.md":"D9wqN7D-","guide_components_gradienttext.md":"DZttkFKU","guide_components_grid.md":"SaASpIlS","guide_components_highlight.md":"CEMiNrhs","guide_components_image.md":"BxGcLItb","guide_components_input.md":"TYsLHbMH","guide_components_inputnumber.md":"3X2-oTX0","guide_components_inputsearch.md":"BR4_fJaJ","guide_components_list.md":"BjxNhZob","guide_components_loadingbar.md":"BvnDWbuY","guide_components_message.md":"B1oCSepz","guide_components_modal.md":"DQfGAkJn","guide_components_notification.md":"Bqfx6rmu","guide_components_numberanimation.md":"Bral6r8V","guide_components_pagination.md":"BSDIHxqt","guide_components_popconfirm.md":"Ma1qesbZ","guide_components_popover.md":"BTlMU0mc","guide_components_progress.md":"BgCbx87p","guide_components_qrcode.md":"DaJ4XPWO","guide_components_radio.md":"CqhrbjD_","guide_components_rate.md":"pPHWSvC2","guide_components_result.md":"D-lQRTCI","guide_components_scrollbar.md":"BPSnfaHF","guide_components_segmented.md":"CNKtHD7C","guide_components_select.md":"DCNNsZ8F","guide_components_skeleton.md":"DiabiqGO","guide_components_slider.md":"BVE7_hiq","guide_components_space.md":"DFi2Vq9V","guide_components_spin.md":"DLo6XfNJ","guide_components_statistic.md":"DI16D3sD","guide_components_steps.md":"ZGsQ8EQh","guide_components_swiper.md":"Bk4rYfqL","guide_components_switch.md":"B4Gedvj4","guide_components_table.md":"DkN2jMZ0","guide_components_tabs.md":"B-623vNL","guide_components_tag.md":"lOTEjK53","guide_components_textarea.md":"DtoDorUt","guide_components_textscroll.md":"lU6_5anK","guide_components_timeline.md":"BPp0owXX","guide_components_tooltip.md":"Duir1lqQ","guide_components_upload.md":"9gVAPdOF","guide_components_video.md":"DDUicSif","guide_components_waterfall.md":"BE-jDjH3","guide_components_watermark.md":"BW9fpjc8","guide_customize.md":"D8vJH_v2","guide_features.md":"L8hD5DnR","guide_ondemand.md":"B1YX8vn5","guide_started.md":"nl7W1Fjd","guide_template.md":"CQJaijVB","index.md":"CZXC_9iE","sponsor_charge.md":"Czhd2_CI","utils_functions_add.md":"DM7sxA_0","utils_functions_date-format.md":"BfSsumlJ","utils_functions_debounce.md":"DzK5ZrIn","utils_functions_download-file.md":"BULIZuaQ","utils_functions_event-listener.md":"DlqTQ7Bx","utils_functions_format-number.md":"DGvgCEGz","utils_functions_fps.md":"Dg30L6qJ","utils_functions_injection.md":"F9vZ2pVU","utils_functions_media-query.md":"7S3Yc0iG","utils_functions_mutation-observer.md":"CIkfZJVM","utils_functions_raf-timeout.md":"DOUCa1I5","utils_functions_resize-observer.md":"BwcBcbqM","utils_functions_scroll.md":"CKmUMzP9","utils_functions_slots-exist.md":"X_zCkkb6","utils_functions_throttle.md":"DzYXQaWu","utils_functions_toggle-dark.md":"VAy4Ft-k","utils_started.md":"CXF_uMfd"}
