{"guide_changelog.md":"B7f_Jpe3","guide_components_alert.md":"CpeY8-xA","guide_components_avatar.md":"Du0Xmxs2","guide_components_backtop.md":"B6ts_e2F","guide_components_badge.md":"nHc7oUOI","guide_components_breadcrumb.md":"ewL7poL6","guide_components_button.md":"DddxihkZ","guide_components_card.md":"CXN87JLZ","guide_components_carousel.md":"CQ0ij5Zr","guide_components_cascader.md":"CfnMwD1b","guide_components_checkbox.md":"63fcQO5q","guide_components_collapse.md":"C2_ETNAT","guide_components_countdown.md":"BG9cfpwZ","guide_components_datepicker.md":"QNzEnZbZ","guide_components_descriptions.md":"DJ_IVm-6","guide_components_dialog.md":"C_8y84Qh","guide_components_divider.md":"Bvx3k0sV","guide_components_drawer.md":"B62mfQRV","guide_components_ellipsis.md":"D1ck_CGi","guide_components_empty.md":"dcrhivU7","guide_components_flex.md":"B9FCpZnZ","guide_components_floatbutton.md":"jFzOe5sW","guide_components_gradienttext.md":"FCvIKQMo","guide_components_grid.md":"Dc9vG-Vw","guide_components_image.md":"DDyZc4iY","guide_components_input.md":"tZBM5AlP","guide_components_inputnumber.md":"RzRL_P5q","guide_components_inputsearch.md":"CpIw2T0H","guide_components_list.md":"ZmQ3EErh","guide_components_loadingbar.md":"CMxAKePc","guide_components_message.md":"Co_3elW0","guide_components_modal.md":"CXfH2Ain","guide_components_notification.md":"YHD98frr","guide_components_numberanimation.md":"CJJLKyZR","guide_components_pagination.md":"CEShxNG1","guide_components_popconfirm.md":"DzBWNIck","guide_components_popover.md":"aotFssUB","guide_components_progress.md":"Cf7VWpXb","guide_components_qrcode.md":"C7UO_kax","guide_components_radio.md":"ThZSVEB1","guide_components_rate.md":"ClvKwY_v","guide_components_result.md":"BH5nIg4w","guide_components_scrollbar.md":"BwV4IImB","guide_components_segmented.md":"DKYT4Olh","guide_components_select.md":"BKF6TY-s","guide_components_skeleton.md":"ChiWYV-8","guide_components_slider.md":"CKwkSZFA","guide_components_space.md":"SePriNjW","guide_components_spin.md":"DANCpEQ7","guide_components_statistic.md":"CshZCIpu","guide_components_steps.md":"Dd-23cVS","guide_components_swiper.md":"CztXbxyY","guide_components_switch.md":"Bmvwfowp","guide_components_table.md":"B1Rln70a","guide_components_tabs.md":"B_Zvh-GE","guide_components_tag.md":"BI5u1yFY","guide_components_textarea.md":"ChLyi5Xz","guide_components_textscroll.md":"Dl4VCjrJ","guide_components_timeline.md":"NGZTr5Ip","guide_components_tooltip.md":"BuycGa3t","guide_components_upload.md":"C7PwMXu3","guide_components_video.md":"DmJfJ5Eg","guide_components_waterfall.md":"DanVALRj","guide_components_watermark.md":"CHq56kg7","guide_features.md":"9nhrrzQe","guide_ondemand.md":"D7-MNeL1","guide_started.md":"BUhXq-Wj","guide_template.md":"CwHdZwlq","index.md":"BvNHyoEW","sponsor_charge.md":"Bcb8orwg","utils_functions_add.md":"rzbbbRT8","utils_functions_date-format.md":"CKreqR5o","utils_functions_debounce.md":"BCEHsLDq","utils_functions_download-file.md":"D98BcTzU","utils_functions_event-listener.md":"BcK74uuY","utils_functions_format-number.md":"DBuM6v0M","utils_functions_fps.md":"y4BndqAk","utils_functions_media-query.md":"CuU-SWWj","utils_functions_mutation-observer.md":"D0AA8Ywo","utils_functions_raf-timeout.md":"5TSMlIcF","utils_functions_resize-observer.md":"D4g5COtD","utils_functions_scroll.md":"CwFa-4fb","utils_functions_slots-exist.md":"CrZWsYhk","utils_functions_throttle.md":"bZ3XZL9r","utils_functions_toggle-dark.md":"MgL3AUCj","utils_started.md":"BlJNMzL3"}
