{"guide_changelog.md":"B_UMGfgJ","guide_components_alert.md":"qwokXSUy","guide_components_avatar.md":"BU1R6XLJ","guide_components_backtop.md":"DBP_qors","guide_components_badge.md":"C5PprFoH","guide_components_breadcrumb.md":"-MslDOVn","guide_components_button.md":"salhwYd3","guide_components_card.md":"B6URRAcs","guide_components_carousel.md":"oWJ1z3K1","guide_components_cascader.md":"CGJe78QC","guide_components_checkbox.md":"C3FaUyVF","guide_components_collapse.md":"C2D0KZfR","guide_components_countdown.md":"CoOsRQk-","guide_components_datepicker.md":"CxOAD_zF","guide_components_descriptions.md":"B6HUzlPZ","guide_components_dialog.md":"DOTpF6vh","guide_components_divider.md":"B1z8CMXr","guide_components_drawer.md":"CSy8U27j","guide_components_ellipsis.md":"Di8eJ1kC","guide_components_empty.md":"CZEGqBcp","guide_components_flex.md":"D0ovq4uV","guide_components_floatbutton.md":"Bvn9rc6e","guide_components_gradienttext.md":"BiiXDuZt","guide_components_grid.md":"BCAbPWtl","guide_components_image.md":"CGsS36Tu","guide_components_input.md":"D2AxHJec","guide_components_inputnumber.md":"B6bgun34","guide_components_inputsearch.md":"BDI5ZGuM","guide_components_list.md":"C2gm3nwb","guide_components_loadingbar.md":"DQcPSf63","guide_components_message.md":"BNFAUW29","guide_components_modal.md":"CLG_4PKd","guide_components_notification.md":"CDnEnx0I","guide_components_numberanimation.md":"B_l4ZGnd","guide_components_pagination.md":"jrxwXZOu","guide_components_popconfirm.md":"DSl9Is0b","guide_components_popover.md":"CRqvGBG_","guide_components_progress.md":"DTw8FdMR","guide_components_qrcode.md":"Ce4tCCwA","guide_components_radio.md":"Cwmcvos5","guide_components_rate.md":"BwBPTTKt","guide_components_result.md":"D0xZ91QS","guide_components_scrollbar.md":"LF67khr_","guide_components_segmented.md":"cf5wh8Ph","guide_components_select.md":"Dj6WoPrF","guide_components_skeleton.md":"Cou_Qlfj","guide_components_slider.md":"Dc64ihwF","guide_components_space.md":"BuyqjWnC","guide_components_spin.md":"BwupIQGO","guide_components_statistic.md":"Ddhl2aJN","guide_components_steps.md":"DDeaU7CX","guide_components_swiper.md":"6hkjvrXf","guide_components_switch.md":"CgP_3Qir","guide_components_table.md":"4oL1jbFj","guide_components_tabs.md":"DdClMbJC","guide_components_tag.md":"nXBzY2U3","guide_components_textarea.md":"Bya74eq2","guide_components_textscroll.md":"CCKuYVYD","guide_components_timeline.md":"CbhdjFFm","guide_components_tooltip.md":"BcTYVNF0","guide_components_upload.md":"DKSLoo3Q","guide_components_video.md":"Dj1EZeyl","guide_components_waterfall.md":"BIVxV2tL","guide_components_watermark.md":"BW2J_1ap","guide_features.md":"CiT8qfi0","guide_started.md":"B76r07Qs","guide_template.md":"CIqwkR8s","index.md":"6QC9rvlH","sponsor_charge.md":"BYg7hCNX","utils_functions_add.md":"CIcSGhXW","utils_functions_date-format.md":"BTG4poej","utils_functions_debounce.md":"DwM_4FvN","utils_functions_download-file.md":"Dm2Uew__","utils_functions_event-listener.md":"CShkrF2O","utils_functions_format-number.md":"1svdReJL","utils_functions_fps.md":"h71n2GwO","utils_functions_media-query.md":"BN5WgJ4B","utils_functions_mutation-observer.md":"BP5i-IoP","utils_functions_raf-timeout.md":"ByJDV7Qj","utils_functions_resize-observer.md":"CaSXrUMI","utils_functions_scroll.md":"C9xwCvMm","utils_functions_slots-exist.md":"23AUUlbm","utils_functions_throttle.md":"DvBoHtMq","utils_functions_toggle-dark.md":"BEi6rDwF","utils_started.md":"BgNm95Ls"}
